odoo/addons/pos_order_mgmt/README.rst
odoo/addons/pos_order_mgmt/__init__.py
odoo/addons/pos_order_mgmt/__manifest__.py
odoo/addons/pos_order_mgmt/i18n/ca.po
odoo/addons/pos_order_mgmt/i18n/es.po
odoo/addons/pos_order_mgmt/i18n/fr.po
odoo/addons/pos_order_mgmt/i18n/it.po
odoo/addons/pos_order_mgmt/i18n/pos_order_mgmt.pot
odoo/addons/pos_order_mgmt/i18n/pt.po
odoo/addons/pos_order_mgmt/models/__init__.py
odoo/addons/pos_order_mgmt/models/pos_config.py
odoo/addons/pos_order_mgmt/models/pos_order.py
odoo/addons/pos_order_mgmt/readme/CONFIGURE.rst
odoo/addons/pos_order_mgmt/readme/CONTRIBUTORS.rst
odoo/addons/pos_order_mgmt/readme/DESCRIPTION.rst
odoo/addons/pos_order_mgmt/readme/ROADMAP.rst
odoo/addons/pos_order_mgmt/readme/USAGE.rst
odoo/addons/pos_order_mgmt/static/description/Screenshot_127.png
odoo/addons/pos_order_mgmt/static/description/icon.png
odoo/addons/pos_order_mgmt/static/description/index.html
odoo/addons/pos_order_mgmt/static/description/order-mgmt-config.png
odoo/addons/pos_order_mgmt/static/description/order-mgmt-icon.png
odoo/addons/pos_order_mgmt/static/src/js/CopyOrderButton.js
odoo/addons/pos_order_mgmt/static/src/js/ProductScreen.js
odoo/addons/pos_order_mgmt/static/src/js/RefundOrderButton.js
odoo/addons/pos_order_mgmt/static/src/js/models.js
odoo/addons/pos_order_mgmt/static/src/xml/CopyOrderButton.xml
odoo/addons/pos_order_mgmt/static/src/xml/RefundOrderButton.xml
odoo/addons/pos_order_mgmt/views/assets.xml
odoo/addons/pos_order_mgmt/views/view_pos_config.xml
odoo14_addon_pos_order_mgmt-14.0.1.0.2.dist-info/METADATA
odoo14_addon_pos_order_mgmt-14.0.1.0.2.dist-info/WHEEL
odoo14_addon_pos_order_mgmt-14.0.1.0.2.dist-info/top_level.txt
odoo14_addon_pos_order_mgmt-14.0.1.0.2.dist-info/RECORD
